{
    "lng_intro_about2": "Welcome to the 64Gram Desktop app.\nIt's fast and secure.",

    "lng_settings_enhanced": "Додаткові",
    "lng_settings_network": "Мережа",
    "lng_settings_net_speed_boost": "Прискорення завантаження",
    "lng_settings_show_message_id": "Відображати ID",
    "lng_settings_button": "Кнопки",
    "lng_settings_show_emoji_button_as_text": "Букви замість емодзі",
    "lng_settings_show_repeater_option": "«Повторити» в контекстному меню",
    "lng_settings_show_phone_number": "Відображати номер",
	"lng_settings_repeater_reply_to_orig_msg": "Відповісти на вихідне",
    "lng_settings_disable_cloud_draft_sync": "Вимкнути синхронізацію чернеток",
    "lng_settings_hide_classic_forward": "Сховати класичне пересилання",
    "lng_settings_show_scheduled_button": "Відображати кнопку запланованих",
    "lng_settings_voice_chat": "Голосовий чат",
    "lng_settings_stereo_mode": "Enable Stereo Mode",
    "lng_settings_pin_voice_chat": "Pin To Top",
    "lng_settings_unpin_voice_chat": "Unpin",
    "lng_settings_radio_controller": "Радіо-контролер ",
    "lng_settings_auto_unmute": "Авто-увімкнення звуку",
    "lng_settings_other": "Інше",
    "lng_settings_hide_all_chats": "Приховати папку «Усі чати»",
    "lng_settings_replace_edit_button": "Replace \"Edit\" button by Saved Messages",
    "lng_settings_disable_link_warning": "Disable open link warning",
    "lng_settings_hide_messages": "Hide messages from blocked user",
    "lng_settings_restart_hint": "УВАГА: зміна параметрів прописаних червоним кольором, перезапустять додаток для застосування.",

    "lng_settings_skip_message": "Skip to next unread chat",
    "lng_settings_skip_message_desc": "Note: Allow ALT+↑/↓ shortcut to skip to next unread chat",

    "lng_net_speed_boost_title": "Прискорення завантаження",
    "lng_net_speed_boost_desc": "Увага: високі значення параметра при повільному інтернеті можуть зробити ще гірше. Використовуйте на свій страх і ризик.",
    "lng_show_emoji_button_as_text_desc": "Примітка: Якщо ви не бачите емодзі на кнопках, включіть цю опцію.",
    "lng_radio_controller_desc": "Радіо-контролер — це експериментальний бот для управління аудіо-трансляцією.",
    "lng_auto_unmute_desc": "Автоматичне включення звуку при вході в голосовий чат.",
    "lng_settings_hide_messages_desc": "Note: IT IS NOT REALLY HIDE! Messages are still available to view, but text will be converted to Spoiler and media won't auto download.",
	
    "lng_net_speed_boost_default": "Відключено",
    "lng_net_speed_boost_slight": "Трішки",
    "lng_net_speed_boost_medium": "Середнє",
    "lng_net_speed_boost_big": "Високе",

    "lng_net_boost_restart_desc": "Для збереження змін потрібен перезапуск додатку.\n\nПерезапустити зараз?",
    "lng_show_messages_id_desc": "Увага: Для збереження змін потрібен перезапуск додатку.",

    "lng_chat_restriction_reason": "Причина обмеження",
    "lng_copy_restriction_reason": "Причина обмеження копіювання",

    "lng_context_copy_callback_data": "Копіювати дані зворотного виклику",
    "lng_context_forward_selected_no_quote": "Переслати виділене без автора",
    "lng_selected_forward_no_quote": "Переслати без автора",
    "lng_context_forward_msg_old_selected": "Переслати виділене (Classic)",
    "lng_selected_forward_emoji_classic": "📠(Classic)",

    "lng_message_id": "ID повідомлення: ",

    "lng_admin_log_banned_send_stickers2": "Надсилати наліпки",
    "lng_admin_log_banned_send_gifs": "Надсилати GIF",
    "lng_admin_log_banned_send_games": "Надсилати ігри",
    "lng_admin_log_banned_use_inline": "Використовувати інлайн-ботів",
    "lng_rights_chat_send_stickers2": "Надсилати наліпки",
    "lng_rights_chat_send_gifs": "Надсилати GIF",
    "lng_rights_chat_send_games": "Надсилати ігри",
    "lng_rights_chat_use_inline": "Використовувати інлайн-ботів",

    "lng_media_selected_gif#one": "{count} GIF",
    "lng_media_selected_gif#other": "{count} GIF",
    "lng_media_type_gifs": "GIF",
    "lng_profile_gifs#one": "{count} GIF",
    "lng_profile_gifs#other": "{count} GIF",
    "lng_profile_gifs_header": "GIF",
    "lng_media_gif_empty": "Тут немає жодного GIF",

    "lng_create_supergroup_title": "Створити супергрупу",
    "lng_action_group_migrate": "Група була перетворена в супергрупу",
    "lng_sure_upgrade_group": "Ви впевнені, що хочете перетворити цю групу в супергрупу?",
    "lng_chat_upgrade_warning": "Увага: Цю дію неможливо скасувати.",
	
    "lng_user_not_found": "Користувача не знайдено. \nПримітка: перш ніж робити посилання на користувача, вам потрібно відкрити його профіль через цей клієнт.",
    
    "lng_settings_always_delete_for": "Always select delete for",
    "lng_settings_delete_disabled": "Ніколи",
    "lng_settings_delete_for_group": "У групах",
    "lng_settings_delete_for_person": "В особистих чатах",
    "lng_settings_delete_for_both": "Завжди",
	
    "lng_title_forward_as_copy": "Копіювати в...",
    "lng_title_multiple_forward": "Переслати в...",

    "lng_context_forward_msg": "Мульти-пересилання",
    "lng_context_forward_msg_old": "Переслати (Classic)",
    "lng_context_show_messages_from": "Повідомлення користувача",
    "lng_context_repeat_msg": "Повторити",
    "lng_context_repeat_msg_no_fwd": "Повторити відповіддю",
    "lng_context_forward_msg_no_quote": "Переслати без автора",
    "lng_forward_to_saved_message": "Переслати в Збережене",
    "lng_context_repeater": "Repeater",
    "lng_context_forward": "Forward",

    "lng_settings_enable_hd_video": "Higher video bitrate",
    "lng_hd_video_hint": "Video bitrate is changed! Rejoin a voice chat if you've already joined.",

    "lng_bitrate_controller": "Audio Bitrate",
    "lng_bitrate_controller_desc": "Високе значення може нашкодити учасникам з повільним інтернетом.",
    "lng_bitrate_controller_hint": "Audio bitrate is changed! Rejoin a voice chat if you've already joined.",

    "lng_bitrate_controller_default": "Default (32 Kbps)",
    "lng_bitrate_controller_64k": "64 Kbps",
    "lng_bitrate_controller_96k": "96 Kbps",
    "lng_bitrate_controller_128k": "128 Kbps",
    "lng_bitrate_controller_160k": "160 Kbps",
    "lng_bitrate_controller_192k": "192 Kbps",
    "lng_bitrate_controller_256k": "256 Kbps",
    "lng_bitrate_controller_320k": "320 Kbps",

    "lng_pinned_message_show": "Показати закріплені",
    "lng_pinned_message_hide": "Приховати закріплені",
    "lng_pinned_message_view": "Відкрити закріплені",
    "lng_go_to_first_message": "Go to first message",

    "lng_proxy_remove_all": "Видалити всі проксі",
    
    "lng_copy_profile_id": "ID copied to clipboard."
}
